pynteny/__init__.py
pynteny/cli.py
pynteny/src/__init__.py
pynteny/src/api.py
pynteny/src/filter.py
pynteny/src/hmm.py
pynteny/src/parser.py
pynteny/src/preprocessing.py
pynteny/src/subcommands.py
pynteny/src/utils.py
pynteny/src/wrappers.py
pynteny/src/app/__init__.py
pynteny/src/app/components.py
pynteny/src/app/helpers.py
pynteny/src/app/main_page.py
pynteny/src/app/assets/script.js
pynteny/src/app/assets/styles.css
pynteny/src/app/assets/img/favicon.png
pynteny/src/app/assets/img/logo.png
pynteny/tests/test_integration_search.py
pynteny/tests/test_parser.py
pynteny/tests/test_preprocessing.py
pynteny/tests/test_data/MG1655.fasta
pynteny/tests/test_data/MG1655.gb
pynteny/tests/test_data/hmm_meta.tsv
pynteny/tests/test_data/hmms/TIGR00170.1.HMM
pynteny/tests/test_data/hmms/TIGR00171.1.HMM
pynteny/tests/test_data/hmms/TIGR00973.1.HMM
pynteny-0.0.2.dist-info/LICENSE
pynteny-0.0.2.dist-info/METADATA
pynteny-0.0.2.dist-info/WHEEL
pynteny-0.0.2.dist-info/entry_points.txt
pynteny-0.0.2.dist-info/top_level.txt
pynteny-0.0.2.dist-info/RECORD
